geograph/__init__.py
geograph/_version.py
geograph/binary_graph_operations.py
geograph/constants.py
geograph/geograph.py
geograph/geotimeline.py
geograph/metrics.py
geograph/utils/__init__.py
geograph/utils/geopandas_utils.py
geograph/utils/polygon_utils.py
geograph/utils/rasterio_utils.py
geograph/visualisation/__init__.py
geograph/visualisation/control_widgets.py
geograph/visualisation/folium_utils.py
geograph/visualisation/geoviewer.py
geograph/visualisation/graph_utils.py
geograph/visualisation/style.py
geograph/visualisation/widget_utils.py
src/__init__.py
src/_version.py
src/binary_graph_operations.py
src/constants.py
src/geograph.py
src/geotimeline.py
src/metrics.py
src/utils/__init__.py
src/utils/geopandas_utils.py
src/utils/polygon_utils.py
src/utils/rasterio_utils.py
src/visualisation/__init__.py
src/visualisation/control_widgets.py
src/visualisation/folium_utils.py
src/visualisation/geoviewer.py
src/visualisation/graph_utils.py
src/visualisation/style.py
src/visualisation/widget_utils.py
geograph-0.0.2.dist-info/LICENSE
geograph-0.0.2.dist-info/METADATA
geograph-0.0.2.dist-info/WHEEL
geograph-0.0.2.dist-info/top_level.txt
geograph-0.0.2.dist-info/RECORD
