Metadata-Version: 2.1
Name: geograph
Version: 0.0.2
Summary: Group Team Challenge 2021 - Biodiversity Team
Home-page: https://geograph.readthedocs.io/
Author: Biodiversity Team
Author-email: hb574@cam.ac.uk
License: MIT
Platform: UNKNOWN
Classifier: Development Status :: 3 - Alpha
Classifier: License :: OSI Approved :: MIT License
Classifier: Intended Audience :: Science/Research
Classifier: Intended Audience :: Developers
Classifier: Programming Language :: Python
Classifier: Programming Language :: Python :: 3
Classifier: Programming Language :: Python :: 3.8
Classifier: Programming Language :: Python :: 3.9
Classifier: Programming Language :: Python :: 3.10
Classifier: Programming Language :: Python :: 3 :: Only
Classifier: Programming Language :: Python :: Implementation :: CPython
Classifier: Topic :: Scientific/Engineering :: GIS
Classifier: Typing :: Typed
Classifier: Operating System :: Microsoft :: Windows
Classifier: Operating System :: POSIX
Classifier: Operating System :: Unix
Classifier: Operating System :: MacOS
Requires-Python: >=3.8.0
Requires-Dist: numpy
Requires-Dist: pandas
Requires-Dist: folium
Requires-Dist: ipyleaflet
Requires-Dist: tqdm
Requires-Dist: geopandas
Requires-Dist: shapely
Requires-Dist: rtree
Requires-Dist: rasterio (==1.1.8)
Requires-Dist: xarray
Requires-Dist: networkx
